digitalhub_core/__init__.py
digitalhub_core/client/__init__.py
digitalhub_core/client/builder.py
digitalhub_core/client/objects/__init__.py
digitalhub_core/client/objects/base.py
digitalhub_core/client/objects/dhcore.py
digitalhub_core/client/objects/local.py
digitalhub_core/context/__init__.py
digitalhub_core/context/builder.py
digitalhub_core/context/context.py
digitalhub_core/entities/__init__.py
digitalhub_core/entities/entity_types.py
digitalhub_core/entities/registries.py
digitalhub_core/entities/utils.py
digitalhub_core/entities/_base/__init__.py
digitalhub_core/entities/_base/api.py
digitalhub_core/entities/_base/base.py
digitalhub_core/entities/_base/crud.py
digitalhub_core/entities/_base/metadata.py
digitalhub_core/entities/_base/state.py
digitalhub_core/entities/_base/entity/__init__.py
digitalhub_core/entities/_base/entity/base.py
digitalhub_core/entities/_base/entity/context.py
digitalhub_core/entities/_base/entity/executable.py
digitalhub_core/entities/_base/entity/material.py
digitalhub_core/entities/_base/entity/unversioned.py
digitalhub_core/entities/_base/entity/versioned.py
digitalhub_core/entities/_base/spec/__init__.py
digitalhub_core/entities/_base/spec/base.py
digitalhub_core/entities/_base/spec/material.py
digitalhub_core/entities/_base/status/__init__.py
digitalhub_core/entities/_base/status/base.py
digitalhub_core/entities/_base/status/material.py
digitalhub_core/entities/_builders/__init__.py
digitalhub_core/entities/_builders/metadata.py
digitalhub_core/entities/_builders/name.py
digitalhub_core/entities/_builders/spec.py
digitalhub_core/entities/_builders/status.py
digitalhub_core/entities/_builders/uuid.py
digitalhub_core/entities/artifact/__init__.py
digitalhub_core/entities/artifact/builder.py
digitalhub_core/entities/artifact/crud.py
digitalhub_core/entities/artifact/spec.py
digitalhub_core/entities/artifact/status.py
digitalhub_core/entities/artifact/entity/__init__.py
digitalhub_core/entities/artifact/entity/_base.py
digitalhub_core-0.7.1.dist-info/LICENSE.txt
digitalhub_core-0.7.1.dist-info/METADATA
digitalhub_core-0.7.1.dist-info/WHEEL
digitalhub_core-0.7.1.dist-info/top_level.txt
digitalhub_core-0.7.1.dist-info/RECORD
