Metadata-Version: 2.1
Name: digitalhub-core
Version: 0.7.1
Summary: Python SDK for DHCore core layer
Author-email: Fondazione Bruno Kessler <dslab@fbk.eu>, Matteo Martini <mmartini@fbk.eu>
License: Apache License
Project-URL: Homepage, https://github.com/scc-digitalhub/digitalhub-sdk
Keywords: data,dataops,kubernetes
Classifier: License :: OSI Approved :: Apache Software License
Classifier: Programming Language :: Python :: 3.9
Classifier: Programming Language :: Python :: 3.10
Requires-Python: >=3.9
License-File: LICENSE.txt
Requires-Dist: boto3
Requires-Dist: pydantic<2
Requires-Dist: sqlalchemy<2
Requires-Dist: pyarrow
Requires-Dist: numpy<2
Requires-Dist: requests
Requires-Dist: PyYAML
Requires-Dist: python-dotenv
Provides-Extra: dev
Requires-Dist: black; extra == "dev"
Requires-Dist: pytest; extra == "dev"
Requires-Dist: bumpver; extra == "dev"
Requires-Dist: ruff; extra == "dev"
Requires-Dist: moto; extra == "dev"
Provides-Extra: docs
Requires-Dist: Sphinx>=7; extra == "docs"
Requires-Dist: pydata-sphinx-theme>=0.15; extra == "docs"
Requires-Dist: numpydoc>=1.6; extra == "docs"
Provides-Extra: full
Requires-Dist: GitPython>=3; extra == "full"
Requires-Dist: psycopg2-binary; extra == "full"
